{
  "id": "nk模型",
  "name": "NK模型",
  "label": "NK模型",
  "icon": "BrainCircuit",
  "description": "考夫曼提出。N 代表系统元件数，K 代表元件间的相互依赖（耦合）程度。K 值越高，景观越崎岖，充满无数个“局部最优”山峰，让进化迷失其中。",
  "deepAnalysis": "NK模型是由进化生物学家斯图尔特·考夫曼（Stuart Kauffman）提出的复杂系统理论模型，用于描述系统的适应性景观。其中N代表系统中的元件数量，K代表元件之间的相互依赖（耦合）程度。NK模型通过模拟不同耦合程度下系统的进化路径，揭示了复杂性与适应性之间的关系。当K值较低时，系统景观相对平滑，进化路径较为明确；当K值较高时，景观变得崎岖不平，充满无数个局部最优解，使进化过程变得困难和不确定。这一模型不仅适用于生物学进化，也广泛应用于经济学、组织管理和技术创新等领域。",
  "principle": "1. 复杂性与适应性权衡：系统复杂性（K值）与适应性之间存在复杂的非线性关系\n2. 局部最优陷阱：高耦合系统容易陷入局部最优解，难以找到全局最优\n3. 路径依赖：系统进化路径受到初始条件和历史选择的影响\n4. 模块化优势：适度的模块化可以降低系统耦合度，提高适应性\n5. 探索与利用平衡：在复杂系统中，需要在探索新路径和利用现有路径之间保持平衡。",
  "scope": "复杂系统分析、组织管理、技术创新、产品开发、战略规划、进化生物学",
  "scenario": "1. 产品架构设计：设计复杂产品时，通过降低模块间耦合度提高系统可维护性\n2. 组织管理：企业组织架构调整时，避免部门间过度依赖导致的决策效率低下\n3. 技术选型：选择技术方案时，考虑不同技术组件之间的耦合程度\n4. 战略规划：制定战略时，识别关键决策点之间的相互影响\n5. 创新探索：在创新过程中，平衡深耕现有方向与探索新方向。",
  "tips": "1. 识别耦合度：分析系统中各要素之间的相互依赖程度，K值越高系统越复杂\n2. 模块化设计：将高耦合系统拆分为相对独立的模块，降低整体复杂度\n3. 警惕局部最优：在高耦合系统中，当前最优解可能只是局部山峰，需要主动探索\n4. 路径记录：记录决策路径，避免重复陷入相同的局部最优陷阱\n5. 平衡探索与利用：既要在当前路径深耕，也要定期探索新路径。",
  "practice": "1. 系统诊断：绘制系统要素关系图，识别高耦合区域\n2. 模块化重构：将相互依赖的要素归类，形成相对独立的模块\n3. 景观映射：识别系统中的多个'山峰'（局部最优），避免过早锁定\n4. 探索实验：定期尝试与当前路径不同的新方向，测试是否有更高山峰\n5. 迭代优化：在找到更好的解后，逐步向其靠拢，同时保持对其他路径的关注。",
  "visualDesign": "<div class=\"neu-card\">\n<svg viewBox=\"0 0 1000 650\">\r\n      <g transform=\"translate(500, 325)\">\r\n        <!-- 适应性地表 (山峰与峡谷) -->\r\n        <path d=\"M-400,200 Q-300,-150 -200,50 T0,-100 T200,150 T400,-250\" fill=\"none\" stroke=\"#ef4444\" stroke-width=\"4\" opacity=\"0.2\" />\r\n        \r\n        <!-- 低耦合系统 (K=0) - 平滑平原 -->\r\n        <path d=\"M-400,100 L400,-100\" stroke=\"#10b981\" stroke-width=\"2\" stroke-dasharray=\"10 5\" opacity=\"0.3\" />\r\n        \r\n        <!-- 高耦合系统 (K=N-1) - 崎岖山脉 -->\r\n        <g>\r\n          <path d=\"M-400,200 L-350,50 L-300,180 L-250,-100 L-200,50 L-150,-250 L-100,0 L-50,150 L0,-120 L50,180 L100,-50 L150,220 L200,-100 L250,50 L300,-280 L350,100 L400,-50\" \r\n                fill=\"none\" stroke=\"#ef4444\" stroke-width=\"2\" />\r\n          <circle cx=\"-150\" cy=\"-250\" r=\"10\" fill=\"#ef4444\" class=\"animate-ping\" />\r\n          <text x=\"-150\" y=\"-280\" text-anchor=\"middle\" fill=\"#ef4444\" style=\"font-size: 14px; font-weight: 900;\">局部最优陷阱</text>\r\n        </g>\r\n\r\n        <!-- 登山者 -->\r\n        <circle r=\"15\" fill=\"#ef4444\">\r\n           <animateMotion path=\"M-400,200 L-350,50 L-300,180 L-250,-100 L-200,50\" dur=\"4s\" repeatCount=\"indefinite\" />\r\n        </circle>\r\n\r\n        <text y=\"280\" text-anchor=\"middle\" fill=\"#ef4444\" style=\"font-size: 32px; font-weight: 900;\">复杂度增加 = 景观崎岖化</text>\r\n      </g>\r\n    </svg>\n</div>"
}