{
  "id": "狄德罗效应",
  "name": "狄德罗效应",
  "label": "狄德罗效应",
  "icon": "BrainCircuit",
  "description": "也被称为“配套欲望”。一件精美的新物品，往往会成为旧平衡的破坏者，诱导你为了与其匹配而更换掉所有原本尚可的旧物。",
  "deepAnalysis": "狄德罗效应（Diderot Effect）揭示了消费行为的连锁反应。核心洞见：一件精美的新物品，往往会成为旧平衡的破坏者，诱导你为了与其匹配而更换掉所有原本尚可的旧物。这种'配套欲望'会导致消费失控和财务压力。",
  "principle": "1. 配套欲望：新物品会引发配套更换的欲望\n2. 平衡破坏：新物品破坏原有的消费平衡\n3. 连锁消费：一件新物引发一系列消费\n4. 身份认同：消费与身份认同相互强化\n5. 消费升级：消费水平只升不降的趋势",
  "scope": "个人消费、家庭装修、品牌建设、消费主义研究、财务管理、市场营销",
  "tips": "1. 购物清单：购物前列清单只买清单上的物品\n2. 冷静期：大额消费实施30天冷静期\n3. 断舍离：定期清理不需要的物品\n4. 价值评估：评估实际价值而非外观品牌\n5. 消费限额：为不同类别消费设定限额",
  "practice": "1. 清单购物：购物前列清单只购买清单上的物品\n2. 30天法则：大额消费实施30天冷静期\n3. 断舍离：定期清理不需要的物品\n4. 价值评估：购买前评估实际价值而非外观\n5. 设定限额：为不同类别消费设定明确限额",
  "visualDesign": "<div class=\"neu-card\">\n<svg viewBox=\"0 0 1000 600\">\n      <defs>\n        <marker id=\"arrow\" markerWidth=\"10\" markerHeight=\"10\" refX=\"5\" refY=\"5\" orient=\"auto\"><path d=\"M0,0 L10,5 L0,10 Z\" fill=\"var(--primary-color)\"/></marker>\n      </defs>\n      <!-- 初始诱因 -->\n      <g transform=\"translate(200, 300)\">\n        <rect x=\"-80\" y=\"-130\" width=\"160\" height=\"260\" rx=\"20\" fill=\"var(--primary-color)\" />\n        <text y=\"5\" text-anchor=\"middle\" fill=\"white\" style=\"font-size: 20px; font-weight: 900;\">第一件新物</text>\n        <path d=\"M100,0 L220,0\" stroke=\"var(--primary-color)\" stroke-width=\"4\" stroke-dasharray=\"10 5\" marker-end=\"url(#arrow)\" />\n      </g>\n      <!-- 连锁配套 -->\n      <g opacity=\"0.6\">\n        <circle cx=\"450\" cy=\"300\" r=\"45\" fill=\"#3b82f6\" /><text x=\"450\" y=\"370\" text-anchor=\"middle\" fill=\"#3b82f6\" style=\"font-size: 16px; font-weight: 900;\">配套更换 A</text>\n        <circle cx=\"650\" cy=\"300\" r=\"45\" fill=\"#3b82f6\" /><text x=\"650\" y=\"370\" text-anchor=\"middle\" fill=\"#3b82f6\" style=\"font-size: 16px; font-weight: 900;\">配套更换 B</text>\n        <circle cx=\"850\" cy=\"300\" r=\"45\" fill=\"var(--primary-color)\" /><text x=\"850\" y=\"370\" text-anchor=\"middle\" fill=\"var(--primary-color)\" style=\"font-size: 24px; font-weight: 900;\">财务失控</text>\n      </g>\n      <circle cx=\"200\" cy=\"300\" r=\"120\" fill=\"none\" stroke=\"var(--primary-color)\" stroke-width=\"2\" class=\"animate-ping\" />\n      <text x=\"500\" y=\"100\" text-anchor=\"middle\" fill=\"var(--primary-color)\" style=\"font-size: 32px; font-weight: 900; opacity: 0.1; letter-spacing: 0.2em;\">THE SPIRAL OF CONSUMPTION</text>\n    </svg>\n</div>"
}